digitalocean_manager/__init__.py
digitalocean_manager/__version__.py
digitalocean_manager/client.py
digitalocean_manager/config.py
digitalocean_manager/main.py
digitalocean_manager/project.py
digitalocean_manager/reader.py
digitalocean_manager/run.py
digitalocean_manager/template.py
digitalocean_manager/managers/__init__.py
digitalocean_manager/managers/action.py
digitalocean_manager/managers/droplet.py
digitalocean_manager/managers/ip.py
digitalocean_manager/managers/sshkey.py
digitalocean_manager/managers/volume.py
dom_cli-0.1.4.dist-info/licenses/LICENSE.txt
tests/__init__.py
tests/test_client.py
tests/test_config.py
dom_cli-0.1.4.dist-info/METADATA
dom_cli-0.1.4.dist-info/WHEEL
dom_cli-0.1.4.dist-info/entry_points.txt
dom_cli-0.1.4.dist-info/top_level.txt
dom_cli-0.1.4.dist-info/RECORD
