Metadata-Version: 2.4
Name: dom-cli
Version: 0.1.4
Summary: Digital Ocean manager with CLI functionality
Home-page: https://github.com/lvidarte/digitalocean-manager/
Author: The Cloutfit Team
Author-email: lvidarte@gmail.com
Classifier: Programming Language :: Python :: 3
Classifier: License :: OSI Approved :: Apache Software License
Classifier: Operating System :: OS Independent
Requires-Python: >=3.10
License-File: LICENSE.txt
Requires-Dist: click==8.1.8
Requires-Dist: pydo==0.7.0
Requires-Dist: PyYAML==6.0.2
Requires-Dist: paramiko==3.5.0
Dynamic: author
Dynamic: author-email
Dynamic: classifier
Dynamic: description
Dynamic: description-content-type
Dynamic: home-page
Dynamic: license-file
Dynamic: requires-dist
Dynamic: requires-python
Dynamic: summary
